nonstring/__init__.py
nonstring-0.3.0.dist-info/LICENSE
nonstring-0.3.0.dist-info/METADATA
nonstring-0.3.0.dist-info/WHEEL
nonstring-0.3.0.dist-info/RECORD
