Metadata-Version: 2.1
Name: nonstring
Version: 0.3.0
Summary: 
Author: Matthew Young
Author-email: myoung.space.science@gmail.com
Requires-Python: >=3.10,<4.0
Classifier: Programming Language :: Python :: 3
Classifier: Programming Language :: Python :: 3.10
Classifier: Programming Language :: Python :: 3.11
Classifier: Programming Language :: Python :: 3.12
